{"rows":[{"item":"平朔公司","unit":"万吨","plan":"145.83","complete":"144.70","over":"-1.13","progress":"99.2%","ring":"-16.79","increase":"-10.4%"},
{"item":"进出口公司","unit":"万吨","plan":"20.77","complete":"24.85","over":"4.08","progress":"119.7%","ring":"-6.50","increase":"-20.7%"},
{"item":"&nbsp;&nbsp;&nbsp;&nbsp;朔中公司","unit":"万吨","plan":"9.80","complete":"9.41","over":"-0.39","progress":"96.0%","ring":"-6.87","increase":"-42.2%"},
{"item":"&nbsp;&nbsp;&nbsp;&nbsp;杨涧洗煤厂","unit":"万吨","plan":"5.83","complete":"7.87","over":"2.04","progress":"135.0%","ring":"-0.07","increase":"-0.9%"},
{"item":"中煤华昱公司","unit":"万吨","plan":"19.20","complete":"23.52","over":"4.32","progress":"122.5%","ring":"1.68","increase":"7.7%"},
{"item":"大屯公司","unit":"万吨","plan":"8.87","complete":"10.32","over":"1.43","progress":"116.1%","ring":"0.82","increase":"8.7%"}
]}